hepdata_maker/Submission.py
hepdata_maker/__init__.py
hepdata_maker/checks.py
hepdata_maker/cli.py
hepdata_maker/console.py
hepdata_maker/logs.py
hepdata_maker/useful_functions.py
hepdata_maker/utils.py
hepdata_maker/variable_loading.py
hepdata_maker/version.py
hepdata_maker/.ipynb_checkpoints/__init__-checkpoint.py
hepdata_maker/schemas/0.0.0/defs.json
hepdata_maker/schemas/0.0.0/steering_file.json
hepdata_maker/schemas/0.0.0/table.json
hepdata_maker/schemas/0.0.0/variable.json
hepdata_maker-0.2.1.dist-info/LICENSE
hepdata_maker-0.2.1.dist-info/METADATA
hepdata_maker-0.2.1.dist-info/WHEEL
hepdata_maker-0.2.1.dist-info/entry_points.txt
hepdata_maker-0.2.1.dist-info/top_level.txt
hepdata_maker-0.2.1.dist-info/RECORD
